forecast_model/VERSION
forecast_model/__init__.py
forecast_model/config.yml
forecast_model/forecast.py
forecast_model/train_pipeline.py
forecast_model/config/__init__.py
forecast_model/config/core.py
forecast_model/datasets/CADUSD.csv
forecast_model/datasets/__init__.py
forecast_model/processing/__init__.py
forecast_model/processing/data_manager.py
forecast_model/processing/preprocessing.py
forecast_model/trained_models/__init__.py
forecast_model/trained_models/forecast_model_output_v0.0.1.pkl
Cad_usd_forecast_model-0.0.1.dist-info/METADATA
Cad_usd_forecast_model-0.0.1.dist-info/WHEEL
Cad_usd_forecast_model-0.0.1.dist-info/top_level.txt
Cad_usd_forecast_model-0.0.1.dist-info/RECORD
