Metadata-Version: 2.1
Name: Cad-usd-forecast-model
Version: 0.0.1
Summary: Model for forecasting CAD-USD exchange price.
Home-page: https://github.com/Olaitan94/CADUSD-Price-Forecast/CADUSD-Price-Forecast-Model-Package
Author: Olaitan Lawal
Author-email: Olaitanlawal94@gmail.com
License: BSD-3
Classifier: License :: OSI Approved :: MIT License
Classifier: Programming Language :: Python
Classifier: Programming Language :: Python :: 3
Classifier: Programming Language :: Python :: 3.7
Classifier: Programming Language :: Python :: 3.8
Classifier: Programming Language :: Python :: 3.9
Classifier: Programming Language :: Python :: 3.10
Classifier: Programming Language :: Python :: 3.11
Classifier: Programming Language :: Python :: Implementation :: CPython
Classifier: Programming Language :: Python :: Implementation :: PyPy
Requires-Python: >=3.7.0
Requires-Dist: joblib (==1.2.0)
Requires-Dist: numpy (==1.23.5)
Requires-Dist: pandas (==1.5.2)
Requires-Dist: cython (==0.29.32)
Requires-Dist: pydantic (==1.10.2)
Requires-Dist: pytest (==7.2.0)
Requires-Dist: setuptools (==65.5.0)
Requires-Dist: strictyaml (==1.6.2)
